timd/__init__.py
timd/measure.py
timd-0.0.3.dist-info/WHEEL
timd-0.0.3.dist-info/METADATA
timd-0.0.3.dist-info/RECORD
