Metadata-Version: 1.2
Name: timd
Version: 0.0.3
Summary: timd a simplified way to time your python applications
Home-page: https://github.com/igordertigor/python-timd
License: UNKNOWN
Author: Ingo Fründ
Author-email: pypi@ingofruend.net
